tp_chaos_generator/__init__.py
tp_chaos_generator/chaos_generator.py
tp_chaos_generator/ode_func.py
tp_chaos_generator/py.typed
tp_chaos_generator/triple_pendulum_ode.py
tp_chaos_generator/utils.py
tp_chaos_generator/version.py
tp_chaos_generator-0.7.0.dist-info/LICENSE
tp_chaos_generator-0.7.0.dist-info/METADATA
tp_chaos_generator-0.7.0.dist-info/WHEEL
tp_chaos_generator-0.7.0.dist-info/top_level.txt
tp_chaos_generator-0.7.0.dist-info/RECORD
