Metadata-Version: 2.1
Name: tp-chaos-generator
Version: 0.7.0
Home-page: https://github.com/souradipp76/tp_chaos_generator
Author: souradipp76
Author-email: souradip.iitg@gmail.com
License: MIT
Classifier: Intended Audience :: Science/Research
Classifier: Development Status :: 3 - Alpha
Classifier: License :: OSI Approved :: MIT License
Classifier: Programming Language :: Python :: 3
Classifier: Topic :: Scientific/Engineering
Requires-Python: >=3.8
License-File: LICENSE
Requires-Dist: matplotlib >=1.4.2
Requires-Dist: numpy >=1.1
Requires-Dist: scipy >=1.7.3
Requires-Dist: pytest
Provides-Extra: dev
Requires-Dist: flake8 ; extra == 'dev'
Requires-Dist: mypy ==1.8.0 ; extra == 'dev'
Requires-Dist: black ==24.1.1 ; extra == 'dev'
Requires-Dist: isort ==5.13.2 ; extra == 'dev'
Requires-Dist: pytest ; extra == 'dev'
Requires-Dist: pytest-sphinx ; extra == 'dev'
Requires-Dist: pytest-cov ; extra == 'dev'
Requires-Dist: twine >=1.11.0 ; extra == 'dev'
Requires-Dist: setuptools ; extra == 'dev'
Requires-Dist: wheel ; extra == 'dev'
Requires-Dist: Sphinx <7.3.0,>=4.3.0 ; extra == 'dev'
Requires-Dist: furo ==2024.1.29 ; extra == 'dev'
Requires-Dist: myst-parser <2.1.0,>=0.15.2 ; extra == 'dev'
Requires-Dist: sphinx-copybutton ==0.5.2 ; extra == 'dev'
Requires-Dist: sphinx-autobuild ==2021.3.14 ; extra == 'dev'
Requires-Dist: sphinx-autodoc-typehints ; extra == 'dev'
Requires-Dist: packaging ; extra == 'dev'
